m2c2_datakit/__init__.py
m2c2_datakit/core/__init__.py
m2c2_datakit/core/codebook.py
m2c2_datakit/core/config.py
m2c2_datakit/core/export.py
m2c2_datakit/core/helpers.py
m2c2_datakit/core/importers.py
m2c2_datakit/core/log.py
m2c2_datakit/core/map.py
m2c2_datakit/core/pipeline.py
m2c2_datakit/core/plot.py
m2c2_datakit/core/utils.py
m2c2_datakit/core/validate.py
m2c2_datakit/tasks/__init__.py
m2c2_datakit/tasks/color_dots.py
m2c2_datakit/tasks/color_match.py
m2c2_datakit/tasks/color_shapes.py
m2c2_datakit/tasks/digit_span.py
m2c2_datakit/tasks/even_odd.py
m2c2_datakit/tasks/go_no_go.py
m2c2_datakit/tasks/go_no_go_fade.py
m2c2_datakit/tasks/grid_memory.py
m2c2_datakit/tasks/shopping_list.py
m2c2_datakit/tasks/stroop.py
m2c2_datakit/tasks/symbol_number_matching.py
m2c2_datakit/tasks/symbol_search.py
m2c2_datakit/tasks/trailmaking.py
m2c2_datakit-0.1.93.dist-info/licenses/LICENSE
m2c2_datakit-0.1.93.dist-info/METADATA
m2c2_datakit-0.1.93.dist-info/WHEEL
m2c2_datakit-0.1.93.dist-info/top_level.txt
m2c2_datakit-0.1.93.dist-info/RECORD
