Metadata-Version: 2.4
Name: m2c2-datakit
Version: 0.1.93
Summary: Data management and scoring tools for the M2C2 project
License: GNU GENERAL PUBLIC LICENSE
Requires-Python: >=3.10
License-File: LICENSE
Requires-Dist: numpy
Requires-Dist: pandas
Requires-Dist: scipy
Requires-Dist: matplotlib
Requires-Dist: seaborn
Requires-Dist: ipykernel>=6.29.5
Requires-Dist: logfire>=3.14.1
Requires-Dist: pydantic>=2.11.4
Requires-Dist: tabulate
Requires-Dist: pyreadr
Requires-Dist: python-dotenv
Requires-Dist: openpyxl
Requires-Dist: pyarrow
Requires-Dist: fastparquet
Provides-Extra: dev
Requires-Dist: black>=24.10.0; extra == "dev"
Requires-Dist: flake8>=7.1.1; extra == "dev"
Requires-Dist: isort>=5.13.2; extra == "dev"
Requires-Dist: mypy>=1.13.0; extra == "dev"
Requires-Dist: pandas-stubs>=2.2.3.241126; extra == "dev"
Requires-Dist: types-psutil>=6.1.0.20241102; extra == "dev"
Requires-Dist: twine>=6.1.0; extra == "dev"
Requires-Dist: tomlkit>=0.12.0; extra == "dev"
Requires-Dist: mkdocstrings[python]; extra == "dev"
Requires-Dist: mkdocs-material[all]; extra == "dev"
Dynamic: license-file
